LICENSE
README.md
setup.py
fuzzyname/__init__.py
fuzzyname/core.py
fuzzyname/nickname.py
fuzzyname/version.py
fuzzyname.egg-info/PKG-INFO
fuzzyname.egg-info/SOURCES.txt
fuzzyname.egg-info/dependency_links.txt
fuzzyname.egg-info/requires.txt
fuzzyname.egg-info/top_level.txt