Metadata-Version: 2.1
Name: fuzzyname
Version: 0.2.1
Summary: A simple Python class for easier name matching (especially in academia).
Home-page: https://github.com/yymao/fuzzyname
Author: Yao-Yuan Mao
Author-email: yymao.astro@gmail.com
Maintainer: Yao-Yuan Mao
Maintainer-email: yymao.astro@gmail.com
License: MIT
Download-URL: https://github.com/yymao/fuzzyname/archive/0.2.1.zip
Keywords: fuzzyname
Platform: UNKNOWN
Classifier: Intended Audience :: Science/Research
Classifier: License :: OSI Approved :: MIT License
Classifier: Programming Language :: Python :: 2.7
Classifier: Programming Language :: Python :: 3.6
Classifier: Programming Language :: Python :: 3.7
Classifier: Programming Language :: Python :: 3.8
Classifier: Programming Language :: Python :: 3.9
Classifier: Programming Language :: Python :: 3.10
License-File: LICENSE
